ai_readme-0.1.6.dist-info/licenses/LICENSE
readme_generator/__init__.py
readme_generator/config.py
readme_generator/generator.py
readme_generator/main.py
readme_generator/prompt_templates.py
readme_generator/utils.py
readme_generator/ai_client/__init__.py
readme_generator/ai_client/claude_client.py
readme_generator/ai_client/gemini_client.py
readme_generator/ai_client/openai_client.py
ai_readme-0.1.6.dist-info/METADATA
ai_readme-0.1.6.dist-info/WHEEL
ai_readme-0.1.6.dist-info/entry_points.txt
ai_readme-0.1.6.dist-info/top_level.txt
ai_readme-0.1.6.dist-info/RECORD
